<?xml version="1.0" encoding="utf-8"?>
<manifest
	xmlns:android="http://schemas.android.com/apk/res/android"
	android:sharedUserId="com.google.android.calendar.uid.shared"
	android:versionCode="201306302"
	android:versionName="201306302"
	android:sharedUserLabel="@7F090015"
	package="com.google.android.calendar"
	>
	<uses-sdk
		android:minSdkVersion="15"
		android:targetSdkVersion="18"
		>
	</uses-sdk>
	<uses-permission
		android:name="android.permission.GET_ACCOUNTS"
		>
	</uses-permission>
	<uses-permission
		android:name="android.permission.MANAGE_ACCOUNTS"
		>
	</uses-permission>
	<uses-permission
		android:name="android.permission.INTERNET"
		>
	</uses-permission>
	<uses-permission
		android:name="android.permission.VIBRATE"
		>
	</uses-permission>
	<uses-permission
		android:name="android.permission.READ_CONTACTS"
		>
	</uses-permission>
	<uses-permission
		android:name="android.permission.READ_CALENDAR"
		>
	</uses-permission>
	<uses-permission
		android:name="android.permission.WRITE_CALENDAR"
		>
	</uses-permission>
	<uses-permission
		android:name="android.permission.WAKE_LOCK"
		>
	</uses-permission>
	<uses-permission
		android:name="android.permission.USE_CREDENTIALS"
		>
	</uses-permission>
	<uses-permission
		android:name="android.permission.READ_SYNC_SETTINGS"
		>
	</uses-permission>
	<uses-permission
		android:name="android.permission.RECEIVE_BOOT_COMPLETED"
		>
	</uses-permission>
	<uses-permission
		android:name="com.google.android.googleapps.permission.GOOGLE_AUTH.mail"
		>
	</uses-permission>
	<uses-permission
		android:name="android.permission.READ_SYNC_STATS"
		>
	</uses-permission>
	<uses-permission
		android:name="android.permission.READ_SYNC_SETTINGS"
		>
	</uses-permission>
	<uses-permission
		android:name="android.permission.WRITE_SYNC_SETTINGS"
		>
	</uses-permission>
	<uses-permission
		android:name="com.google.android.googleapps.permission.GOOGLE_AUTH"
		>
	</uses-permission>
	<uses-permission
		android:name="android.permission.SUBSCRIBED_FEEDS_READ"
		>
	</uses-permission>
	<uses-permission
		android:name="android.permission.SUBSCRIBED_FEEDS_WRITE"
		>
	</uses-permission>
	<uses-permission
		android:name="android.permission.READ_CALENDAR"
		>
	</uses-permission>
	<uses-permission
		android:name="android.permission.WRITE_CALENDAR"
		>
	</uses-permission>
	<uses-permission
		android:name="com.google.android.providers.gsf.permission.READ_GSERVICES"
		>
	</uses-permission>
	<uses-permission
		android:name="com.google.android.c2dm.permission.RECEIVE"
		>
	</uses-permission>
	<permission
		android:name="com.google.android.calendar.permission.C2D_MESSAGE"
		android:protectionLevel="0x00000002"
		>
	</permission>
	<uses-permission
		android:name="com.google.android.calendar.permission.C2D_MESSAGE"
		>
	</uses-permission>
	<application
		android:label="@7F090015"
		android:icon="@7F030000"
		android:name="com.android.calendar.CalendarApplication"
		android:taskAffinity="google.android.task.calendar"
		android:backupAgent="com.android.calendar.CalendarBackupAgent"
		android:allowBackup="true"
		android:hardwareAccelerated="true"
		android:requiredAccountType="*"
		>
		<meta-data
			android:name="com.google.android.backup.api_key"
			android:value="..."
			>
		</meta-data>
		<activity
			android:theme="@7F0B0021"
			android:name="com.android.calendar.AllInOneActivity"
			android:exported="true"
			android:launchMode="2"
			android:windowSoftInputMode="0x00000020"
			>
			<intent-filter
				>
				<action
					android:name="android.intent.action.MAIN"
					>
				</action>
				<category
					android:name="android.intent.category.DEFAULT"
					>
				</category>
				<category
					android:name="android.intent.category.LAUNCHER"
					>
				</category>
				<category
					android:name="android.intent.category.APP_CALENDAR"
					>
				</category>
			</intent-filter>
			<intent-filter
				>
				<action
					android:name="android.intent.action.VIEW"
					>
				</action>
				<category
					android:name="android.intent.category.DEFAULT"
					>
				</category>
				<data
					android:mimeType="time/epoch"
					>
				</data>
				<data
					android:host="com.android.calendar"
					>
				</data>
				<data
					android:scheme="content"
					>
				</data>
			</intent-filter>
		</activity>
		<activity-alias
			android:name="com.android.calendar.LaunchActivity"
			android:exported="true"
			android:targetActivity="com.android.calendar.AllInOneActivity"
			>
		</activity-alias>
		<activity
			android:theme="@7F0B0021"
			android:name="com.android.calendar.EventInfoActivity"
			android:parentActivityName="com.android.calendar.AllInOneActivity"
			>
			<intent-filter
				>
				<action
					android:name="android.intent.action.VIEW"
					>
				</action>
				<category
					android:name="android.intent.category.DEFAULT"
					>
				</category>
			</intent-filter>
			<intent-filter
				>
				<action
					android:name="android.intent.action.VIEW"
					>
				</action>
				<category
					android:name="android.intent.category.DEFAULT"
					>
				</category>
				<data
					android:mimeType="vnd.android.cursor.item/event"
					>
				</data>
			</intent-filter>
			<meta-data
				android:name="android.support.PARENT_ACTIVITY"
				android:value="com.android.calendar.AllInOneActivity"
				>
			</meta-data>
		</activity>
		<activity
			android:theme="@7F0B0021"
			android:name="com.android.calendar.event.EditEventActivity"
			>
		</activity>
		<activity-alias
			android:name="com.android.calendar.EditEventActivity"
			android:exported="true"
			android:targetActivity="com.android.calendar.event.EditEventActivity"
			>
			<intent-filter
				>
				<action
					android:name="android.intent.action.EDIT"
					>
				</action>
				<action
					android:name="android.intent.action.INSERT"
					>
				</action>
				<category
					android:name="android.intent.category.DEFAULT"
					>
				</category>
				<data
					android:mimeType="vnd.android.cursor.item/event"
					>
				</data>
			</intent-filter>
			<intent-filter
				>
				<action
					android:name="android.intent.action.EDIT"
					>
				</action>
				<action
					android:name="android.intent.action.INSERT"
					>
				</action>
				<category
					android:name="android.intent.category.DEFAULT"
					>
				</category>
				<data
					android:mimeType="vnd.android.cursor.dir/event"
					>
				</data>
			</intent-filter>
		</activity-alias>
		<activity
			android:theme="@android:01030055"
			android:label="@7F090015"
			android:name="com.android.calendar.GoogleCalendarUriIntentFilter"
			android:configChanges="0x000000A0"
			>
			<intent-filter
				android:priority="50"
				>
				<action
					android:name="android.intent.action.VIEW"
					>
				</action>
				<category
					android:name="android.intent.category.DEFAULT"
					>
				</category>
				<category
					android:name="android.intent.category.BROWSABLE"
					>
				</category>
				<data
					android:scheme="http"
					android:host="www.google.com"
					android:pathPrefix="/calendar/event"
					>
				</data>
				<data
					android:scheme="https"
					android:host="www.google.com"
					android:pathPrefix="/calendar/event"
					>
				</data>
				<data
					android:scheme="http"
					android:host="www.google.com"
					android:pathPattern="/calendar/hosted/.*/event"
					>
				</data>
				<data
					android:scheme="https"
					android:host="www.google.com"
					android:pathPattern="/calendar/hosted/.*/event"
					>
				</data>
			</intent-filter>
		</activity>
		<activity
			android:theme="@android:0103006E"
			android:label="@7F090064"
			android:name="com.android.calendar.selectcalendars.SelectVisibleCalendarsActivity"
			>
		</activity>
		<activity
			android:theme="@android:0103006E"
			android:label="@7F090069"
			android:name="com.android.calendar.selectcalendars.SelectSyncedCalendarsMultiAccountActivity"
			>
		</activity>
		<activity
			android:theme="@android:0103006E"
			android:label="@7F0900C1"
			android:name="com.android.calendar.CalendarSettingsActivity"
			>
		</activity>
		<meta-data
			android:name="android.app.default_searchable"
			android:value="com.android.calendar.SearchActivity"
			>
		</meta-data>
		<activity
			android:theme="@7F0B0021"
			android:label="@7F0900A6"
			android:name="com.android.calendar.SearchActivity"
			android:exported="true"
			android:launchMode="1"
			android:windowSoftInputMode="0x00000003"
			>
			<intent-filter
				>
				<action
					android:name="android.intent.action.SEARCH"
					>
				</action>
			</intent-filter>
			<meta-data
				android:name="android.app.searchable"
				android:resource="@7F060005"
				>
			</meta-data>
		</activity>
		<provider
			android:name="com.android.calendar.CalendarRecentSuggestionsProvider"
			android:exported="false"
			android:authorities="com.google.android.calendar.CalendarRecentSuggestionsProvider"
			>
		</provider>
		<activity
			android:theme="@android:0103006F"
			android:name="com.android.calendar.alerts.AlertActivity"
			android:excludeFromRecents="true"
			android:launchMode="3"
			>
		</activity>
		<activity
			android:theme="@android:0103006F"
			android:label="@7F09009B"
			android:name="com.android.calendar.alerts.QuickResponseActivity"
			android:excludeFromRecents="true"
			android:launchMode="3"
			>
		</activity>
		<activity
			android:theme="@android:0103006E"
			android:label="@7F0900C0"
			android:name="com.google.android.calendar.extensions.AboutActivity"
			android:launchMode="3"
			>
		</activity>
		<activity
			android:theme="@android:0103006E"
			android:label="@7F09001E"
			android:name="com.google.android.calendar.extensions.LicenseActivity"
			android:exported="false"
			>
		</activity>
		<receiver
			android:name="com.android.calendar.alerts.AlertReceiver"
			>
			<intent-filter
				>
				<action
					android:name="android.intent.action.EVENT_REMINDER"
					>
				</action>
				<action
					android:name="android.intent.action.TIME_SET"
					>
				</action>
				<data
					android:scheme="content"
					>
				</data>
			</intent-filter>
			<intent-filter
				>
				<action
					android:name="android.intent.action.BOOT_COMPLETED"
					>
				</action>
			</intent-filter>
			<intent-filter
				>
				<action
					android:name="android.intent.action.LOCALE_CHANGED"
					>
				</action>
			</intent-filter>
			<intent-filter
				>
				<action
					android:name="android.intent.action.PROVIDER_CHANGED"
					>
				</action>
				<data
					android:scheme="content"
					>
				</data>
				<data
					android:host="com.android.calendar"
					>
				</data>
			</intent-filter>
		</receiver>
		<receiver
			android:name="com.google.android.calendar.alerts.GCMDismissReceiver"
			android:permission="com.google.android.c2dm.permission.SEND"
			android:exported="true"
			>
			<intent-filter
				>
				<action
					android:name="com.google.android.c2dm.intent.RECEIVE"
					>
				</action>
				<category
					android:name="com.google.android.calendar"
					>
				</category>
			</intent-filter>
		</receiver>
		<receiver
			android:name="com.android.calendar.alerts.GlobalDismissManager"
			android:exported="false"
			>
			<intent-filter
				>
				<action
					android:name="com.android.calendar.alerts.DISMISS"
					>
				</action>
			</intent-filter>
		</receiver>
		<service
			android:name="com.android.calendar.alerts.AlertService"
			>
		</service>
		<service
			android:name="com.android.calendar.alerts.DismissAlarmsService"
			>
		</service>
		<service
			android:name="com.android.calendar.alerts.SnoozeAlarmsService"
			>
		</service>
		<service
			android:name="com.android.calendar.alerts.InitAlarmsService"
			>
		</service>
		<receiver
			android:label="@7F090016"
			android:name="com.android.calendar.widget.CalendarAppWidgetProvider"
			>
			<intent-filter
				>
				<action
					android:name="android.appwidget.action.APPWIDGET_UPDATE"
					>
				</action>
				<action
					android:name="com.google.android.calendar.APPWIDGET_UPDATE"
					>
				</action>
			</intent-filter>
			<meta-data
				android:name="android.appwidget.provider"
				android:resource="@7F060001"
				>
			</meta-data>
		</receiver>
		<receiver
			android:name="com.android.calendar.widget.CalendarAppWidgetService$CalendarFactory"
			>
			<intent-filter
				>
				<action
					android:name="android.intent.action.TIMEZONE_CHANGED"
					>
				</action>
				<action
					android:name="android.intent.action.DATE_CHANGED"
					>
				</action>
				<action
					android:name="android.intent.action.TIME_SET"
					>
				</action>
				<action
					android:name="android.intent.action.LOCALE_CHANGED"
					>
				</action>
			</intent-filter>
			<intent-filter
				>
				<action
					android:name="android.intent.action.PROVIDER_CHANGED"
					>
				</action>
				<data
					android:scheme="content"
					>
				</data>
				<data
					android:host="com.android.calendar"
					>
				</data>
			</intent-filter>
			<intent-filter
				>
				<action
					android:name="com.google.android.calendar.APPWIDGET_SCHEDULED_UPDATE"
					>
				</action>
				<data
					android:scheme="content"
					>
				</data>
				<data
					android:host="com.android.calendar"
					>
				</data>
				<data
					android:mimeType="vnd.android.data/update"
					>
				</data>
			</intent-filter>
		</receiver>
		<service
			android:name="com.android.calendar.widget.CalendarAppWidgetService"
			android:permission="android.permission.BIND_REMOTEVIEWS"
			android:exported="false"
			>
		</service>
		<service
			android:name="com.android.calendar.AsyncQueryServiceHelper"
			>
		</service>
		<service
			android:name="com.google.android.syncadapters.calendar.CalendarSyncAdapterService"
			android:exported="true"
			>
			<intent-filter
				>
				<action
					android:name="android.content.SyncAdapter"
					>
				</action>
			</intent-filter>
			<meta-data
				android:name="android.content.SyncAdapter"
				android:resource="@7F060006"
				>
			</meta-data>
		</service>
		<receiver
			android:name="com.google.android.syncadapters.calendar.CalendarSyncAdapterBroadcastReceiver"
			>
			<intent-filter
				>
				<action
					android:name="android.accounts.LOGIN_ACCOUNTS_CHANGED"
					>
				</action>
			</intent-filter>
		</receiver>
		<service
			android:name="com.google.android.syncadapters.calendar.CalendarSyncAdapterIntentService"
			>
		</service>
		<activity
			android:name="com.google.android.syncadapters.calendar.AuthNotificationActivity"
			>
		</activity>
	</application>
</manifest>
